pquisby/__init__.py
pquisby/command/__init__.py
pquisby/command/compare_benchmark.py
pquisby/command/main.py
pquisby/command/process_benchmark.py
pquisby/lib/__init__.py
pquisby/lib/compare_sheets.py
pquisby/lib/post_processing.py
pquisby/lib/process_result.py
pquisby/lib/util.py
pquisby/lib/benchmarks/__init__.py
pquisby/lib/benchmarks/uperf/__init__.py
pquisby/lib/benchmarks/uperf/comparison.py
pquisby/lib/benchmarks/uperf/graph.py
pquisby/lib/benchmarks/uperf/uperf.py
pquisby/lib/credentials/__init__.py
pquisby/lib/credentials/creds.py
pquisby/lib/pricing/__init__.py
pquisby/lib/pricing/cloud_pricing.py
pquisby/lib/sheet/__init__.py
pquisby/lib/sheet/sheet_util.py
pquisby/lib/sheet/sheetapi.py
tttpquisby-0.0.7.dist-info/LICENSE
tttpquisby-0.0.7.dist-info/METADATA
tttpquisby-0.0.7.dist-info/WHEEL
tttpquisby-0.0.7.dist-info/entry_points.txt
tttpquisby-0.0.7.dist-info/top_level.txt
tttpquisby-0.0.7.dist-info/RECORD
